amux/__init__.py
amux-0.2.1.dist-info/METADATA
amux-0.2.1.dist-info/WHEEL
amux-0.2.1.dist-info/entry_points.txt
amux-0.2.1.dist-info/RECORD
