Metadata-Version: 2.4
Name: amux
Version: 0.2.1
Summary: Multi-agent coordination for AI coding assistants. This package redirects to 'claude-co'.
Project-URL: Homepage, https://github.com/jude-hawrani/claude-co
Project-URL: Repository, https://github.com/jude-hawrani/claude-co
Project-URL: Issues, https://github.com/jude-hawrani/claude-co/issues
Author: Jude Hawrani
License-Expression: MIT
Keywords: agents,ai,claude,codex,collaboration,coordination,mcp
Classifier: Development Status :: 4 - Beta
Classifier: Intended Audience :: Developers
Classifier: License :: OSI Approved :: MIT License
Classifier: Programming Language :: Python :: 3
Classifier: Programming Language :: Python :: 3.9
Classifier: Programming Language :: Python :: 3.10
Classifier: Programming Language :: Python :: 3.11
Classifier: Programming Language :: Python :: 3.12
Requires-Python: >=3.9
Requires-Dist: claude-co>=0.2.1
